ComputerAutomation/__init__.py
OnlineTasks/Nasa.py
OnlineTasks/Whatsapp.py
OnlineTasks/__init__.py
OnlineWorks-0.0.6.dist-info/LICENSE
OnlineWorks-0.0.6.dist-info/METADATA
OnlineWorks-0.0.6.dist-info/WHEEL
OnlineWorks-0.0.6.dist-info/entry_points.txt
OnlineWorks-0.0.6.dist-info/top_level.txt
OnlineWorks-0.0.6.dist-info/RECORD
