Metadata-Version: 2.1
Name: OnlineWorks
Version: 0.0.6
Summary: A simple python pacakage that helps you to perform sevaral online tasks and Computer Automations.
Home-page: https://github.com/pypa/OnlineWorks
Author: Debadrito Dutta
Author-email: dipalidutta312@gmail.com
License: MIT
Platform: UNKNOWN
Classifier: Programming Language :: Python :: 3
Classifier: License :: OSI Approved :: MIT License
Classifier: Operating System :: OS Independent
Requires-Dist: requests
Requires-Dist: bs4
Requires-Dist: opencv-python
Requires-Dist: numpy
Requires-Dist: wikipedia
Requires-Dist: pyautogui
